academic_research_mentor/__init__.py
academic_research_mentor/__main__.py
academic_research_mentor/attachments/__init__.py
academic_research_mentor/attachments/ingest.py
academic_research_mentor/attachments/pdf_loader.py
academic_research_mentor/attachments/summarizer.py
academic_research_mentor/chat_logger.py
academic_research_mentor/citations/__init__.py
academic_research_mentor/citations/aggregator.py
academic_research_mentor/citations/formatter.py
academic_research_mentor/citations/merger.py
academic_research_mentor/citations/models.py
academic_research_mentor/citations/validator.py
academic_research_mentor/cli/__init__.py
academic_research_mentor/cli/args.py
academic_research_mentor/cli/commands.py
academic_research_mentor/cli/main.py
academic_research_mentor/cli/openrouter_setup.py
academic_research_mentor/cli/repl.py
academic_research_mentor/cli/repl_helpers.py
academic_research_mentor/cli/resume.py
academic_research_mentor/cli/session.py
academic_research_mentor/cli.py
academic_research_mentor/core/__init__.py
academic_research_mentor/core/agent.py
academic_research_mentor/core/bootstrap.py
academic_research_mentor/core/execution_engine.py
academic_research_mentor/core/fallback_policy.py
academic_research_mentor/core/orchestrator.py
academic_research_mentor/core/recommendation.py
academic_research_mentor/core/stage_detector.py
academic_research_mentor/core/transparency.py
academic_research_mentor/guidelines_engine/__init__.py
academic_research_mentor/guidelines_engine/config.py
academic_research_mentor/guidelines_engine/formatter.py
academic_research_mentor/guidelines_engine/injector.py
academic_research_mentor/guidelines_engine/loader.py
academic_research_mentor/literature_review/__init__.py
academic_research_mentor/literature_review/build_context.py
academic_research_mentor/literature_review/citation_extractors.py
academic_research_mentor/literature_review/context_format.py
academic_research_mentor/literature_review/debug.py
academic_research_mentor-0.2.0.dist-info/WHEEL
academic_research_mentor-0.2.0.dist-info/entry_points.txt
academic_research_mentor-0.2.0.dist-info/METADATA
academic_research_mentor-0.2.0.dist-info/RECORD
