Metadata-Version: 2.3
Name: academic-research-mentor
Version: 0.2.0
Summary: AI-powered mentor for academic research with CLI and Textual TUI front-ends
Keywords: ai,research,mentor,cli,tui,langchain
Author: MajorTimberWolf
Author-email: MajorTimberWolf <ak0929@srmist.edu.in>
License: MIT License
Classifier: Programming Language :: Python :: 3
Classifier: Programming Language :: Python :: 3.11
Classifier: Programming Language :: Python :: 3.12
Classifier: Programming Language :: Python :: 3.13
Classifier: Environment :: Console
Classifier: Framework :: AsyncIO
Classifier: Intended Audience :: Science/Research
Classifier: License :: OSI Approved :: MIT License
Classifier: Topic :: Scientific/Engineering
Classifier: Topic :: Text Processing :: Linguistic
Requires-Dist: langchain>=0.2
Requires-Dist: langchain-openai>=0.1.22
Requires-Dist: langchain-google-genai>=2.0.6
Requires-Dist: langchain-anthropic>=0.2.4
Requires-Dist: langchain-mistralai>=0.2.1
Requires-Dist: langchain-community>=0.2
Requires-Dist: google-genai>=1.29.0
Requires-Dist: openai>=1.40.0
Requires-Dist: anthropic>=0.34.0
Requires-Dist: mistralai>=0.4.2
Requires-Dist: httpx>=0.27.0
Requires-Dist: langgraph>=0.6.5
Requires-Dist: rich>=14.1.0
Requires-Dist: python-dotenv>=1.0.0
Requires-Dist: ddgs>=9.5.5
Requires-Dist: beautifulsoup4>=4.12.0
Requires-Dist: langchain-text-splitters>=0.2
Requires-Dist: faiss-cpu>=1.12.0
Requires-Dist: pypdf>=6.0.0
Requires-Dist: fastembed>=0.7.3
Requires-Dist: pymupdf>=1.26.4
Requires-Dist: tavily-python>=0.3.3
Requires-Dist: textual>=6.2.1
Requires-Dist: textual>=0.60.0 ; extra == 'tui'
Requires-Python: >=3.11
Project-URL: Homepage, https://github.com/lossfunk/ai-research-mentor
Project-URL: Issues, https://github.com/lossfunk/ai-research-mentor/issues
Project-URL: Repository, https://github.com/lossfunk/ai-research-mentor
Provides-Extra: tui
